[
  {
    "kode": "6105010",
    "nama": "TOBA"
  },
  {
    "kode": "6105020",
    "nama": "MELIAU"
  },
  {
    "kode": "6105060",
    "nama": "KAPUAS"
  },
  {
    "kode": "6105070",
    "nama": "MUKOK"
  },
  {
    "kode": "6105120",
    "nama": "JANGKANG"
  },
  {
    "kode": "6105130",
    "nama": "BONTI"
  },
  {
    "kode": "6105140",
    "nama": "PARINDU"
  },
  {
    "kode": "6105150",
    "nama": "TAYAN HILIR"
  },
  {
    "kode": "6105160",
    "nama": "BALAI"
  },
  {
    "kode": "6105170",
    "nama": "TAYAN HULU"
  },
  {
    "kode": "6105180",
    "nama": "KEMBAYAN"
  },
  {
    "kode": "6105190",
    "nama": "BEDUAI"
  },
  {
    "kode": "6105200",
    "nama": "NOYAN"
  },
  {
    "kode": "6105210",
    "nama": "SEKAYAM"
  },
  {
    "kode": "6105220",
    "nama": "ENTIKONG"
  }
]