[
  {
    "kode": "1471011",
    "nama": "PAYUNG SEKAKI"
  },
  {
    "kode": "1471012",
    "nama": "TUAHMADANI"
  },
  {
    "kode": "1471013",
    "nama": "BINAWIDYA"
  },
  {
    "kode": "1471020",
    "nama": "BUKIT RAYA"
  },
  {
    "kode": "1471021",
    "nama": "MARPOYAN DAMAI"
  },
  {
    "kode": "1471022",
    "nama": "TENAYAN RAYA"
  },
  {
    "kode": "1471023",
    "nama": "KULIM"
  },
  {
    "kode": "1471030",
    "nama": "LIMAPULUH"
  },
  {
    "kode": "1471040",
    "nama": "SAIL"
  },
  {
    "kode": "1471050",
    "nama": "PEKANBARU KOTA"
  },
  {
    "kode": "1471060",
    "nama": "SUKAJADI"
  },
  {
    "kode": "1471070",
    "nama": "SENAPELAN"
  },
  {
    "kode": "1471080",
    "nama": "RUMBAI"
  },
  {
    "kode": "1471082",
    "nama": "RUMBAI BARAT"
  },
  {
    "kode": "1471083",
    "nama": "RUMBAI TIMUR"
  }
]