[
  {
    "kode": "6106010",
    "nama": "KENDAWANGAN"
  },
  {
    "kode": "6106020",
    "nama": "MANIS MATA"
  },
  {
    "kode": "6106030",
    "nama": "MARAU"
  },
  {
    "kode": "6106031",
    "nama": "SINGKUP"
  },
  {
    "kode": "6106032",
    "nama": "AIR UPAS"
  },
  {
    "kode": "6106040",
    "nama": "JELAI HULU"
  },
  {
    "kode": "6106050",
    "nama": "TUMBANG TITI"
  },
  {
    "kode": "6106051",
    "nama": "PEMAHAN"
  },
  {
    "kode": "6106052",
    "nama": "SUNGAI MELAYU RAYAK"
  },
  {
    "kode": "6106060",
    "nama": "MATAN HILIR SELATAN"
  },
  {
    "kode": "6106061",
    "nama": "BENUA KAYONG"
  },
  {
    "kode": "6106070",
    "nama": "MATAN HILIR UTARA"
  },
  {
    "kode": "6106071",
    "nama": "DELTA PAWAN"
  },
  {
    "kode": "6106072",
    "nama": "MUARA PAWAN"
  },
  {
    "kode": "6106090",
    "nama": "NANGA TAYAP"
  },
  {
    "kode": "6106100",
    "nama": "SANDAI"
  },
  {
    "kode": "6106101",
    "nama": "HULU SUNGAI"
  },
  {
    "kode": "6106110",
    "nama": "SUNGAI LAUR"
  },
  {
    "kode": "6106120",
    "nama": "SIMPANG HULU"
  },
  {
    "kode": "6106121",
    "nama": "SIMPANG DUA"
  }
]