[
  {
    "kode": "2171010",
    "nama": "BELAKANG PADANG"
  },
  {
    "kode": "2171020",
    "nama": "BULANG"
  },
  {
    "kode": "2171030",
    "nama": "GALANG"
  },
  {
    "kode": "2171040",
    "nama": "SEI BEDUK"
  },
  {
    "kode": "2171041",
    "nama": "SAGULUNG"
  },
  {
    "kode": "2171050",
    "nama": "NONGSA"
  },
  {
    "kode": "2171051",
    "nama": "BATAM KOTA"
  },
  {
    "kode": "2171060",
    "nama": "SEKUPANG"
  },
  {
    "kode": "2171061",
    "nama": "BATU AJI"
  },
  {
    "kode": "2171070",
    "nama": "LUBUK BAJA"
  },
  {
    "kode": "2171080",
    "nama": "BATU AMPAR"
  },
  {
    "kode": "2171081",
    "nama": "BENGKONG"
  }
]